kepler/__init__.py
kepler/_core.cp38-win_amd64.pyd
kepler/core.py
kepler/version.py
kepler.py-0.0.7.data/data/CMakeLists.txt
kepler.py-0.0.7.data/data/src/lib/main.cpp
kepler.py-0.0.7.dist-info/LICENSE
kepler.py-0.0.7.dist-info/METADATA
kepler.py-0.0.7.dist-info/WHEEL
kepler.py-0.0.7.dist-info/top_level.txt
kepler.py-0.0.7.dist-info/RECORD
