Metadata-Version: 2.1
Name: kepler.py
Version: 0.0.7
Summary: Fast and stable solver for Kepler's equation in Python
Author-email: Dan Foreman-Mackey <foreman.mackey@gmail.com>
License: 
Project-URL: Homepage, https://github.com/dfm/kepler.py
Project-URL: Source, https://github.com/dfm/kepler.py
Project-URL: Bug Tracker, https://github.com/dfm/kepler.py/issues
Classifier: Operating System :: OS Independent
Classifier: Programming Language :: Python :: 3
Classifier: Development Status :: 4 - Beta
Classifier: License :: OSI Approved :: MIT License
Requires-Python: >=3.7
Provides-Extra: test
Provides-Extra: docs
License-File: LICENSE
